livecode_streamer/__init__.py
livecode_streamer/plugins.py
livecode_streamer/renderers/__init__.py
livecode_streamer/renderers/nbconvert_renderer.py
livecode_streamer/renderers/pygment_renderer.py
livecode_streamer/renderers/renderer.py
livecode_streamer/stream.py
livecode_streamer/test/foo
livecode_streamer/uploaders/__init__.py
livecode_streamer/uploaders/aws.py
livecode_streamer/uploaders/azure.py
livecode_streamer/uploaders/git.py
livecode_streamer/uploaders/localhost.py
livecode_streamer/uploaders/ssh.py
livecode_streamer/uploaders/uploader.py
livecode_streamer-0.1.5.dist-info/entry_points.txt
livecode_streamer-0.1.5.dist-info/METADATA
livecode_streamer-0.1.5.dist-info/WHEEL
livecode_streamer-0.1.5.dist-info/RECORD
