Metadata-Version: 2.1
Name: livecode-streamer
Version: 0.1.5
Summary: Tool for educators running "live coding" sessions to make their source files and terminal sessions viewable as read-only webpages, so that students can refer back to off-screen commands as reference.
Home-page: https://github.com/naclomi/livecode-streamer
License: MIT
Author: Naomi Alterman
Author-email: naomila@uw.edu
Requires-Python: >=3.7,<4.0
Classifier: License :: OSI Approved :: MIT License
Classifier: Programming Language :: Python :: 3
Classifier: Programming Language :: Python :: 3.7
Classifier: Programming Language :: Python :: 3.8
Classifier: Programming Language :: Python :: 3.9
Classifier: Programming Language :: Python :: 3.10
Classifier: Programming Language :: Python :: 3.11
Provides-Extra: aws
Provides-Extra: azure
Provides-Extra: git
Provides-Extra: jupyter
Provides-Extra: localhost
Requires-Dist: Pygments (>=2.12.0,<3.0.0)
Requires-Dist: azure-storage-blob (>=12.12.0,<13.0.0) ; extra == "azure"
Requires-Dist: boto3 (>=1.24.23,<2.0.0) ; extra == "aws"
Requires-Dist: dulwich (>=0.20.44,<0.21.0) ; extra == "git"
Requires-Dist: keyring (>=23.6.0,<24.0.0)
Requires-Dist: nbconvert (>=6.5.0,<7.0.0) ; extra == "jupyter"
Requires-Dist: nbformat (>=5.4.0,<6.0.0) ; extra == "jupyter"
Requires-Dist: pyngrok (>=5.1.0,<6.0.0) ; extra == "localhost"
Requires-Dist: watchdog (>=2.1.9,<3.0.0)
Project-URL: Repository, https://github.com/naclomi/livecode-streamer
